pearl/__init__.py
pearl/pipeline.py
pearl/core/__init__.py
pearl/core/paf.py
pearl/core/signal_extractor.py
pearl/experiments/__init__.py
pearl/models/__init__.py
pearl/models/classifiers.py
pearl/models/rag_classifier.py
pearl/utils/__init__.py
pearl/utils/device.py
pearl_h-0.1.2.dist-info/licenses/LICENSE
pearl_h-0.1.2.dist-info/METADATA
pearl_h-0.1.2.dist-info/WHEEL
pearl_h-0.1.2.dist-info/top_level.txt
pearl_h-0.1.2.dist-info/RECORD
